[
  {
  "id": 5247,
  "name": "Corner House Ice Cream",
  "city": "Bangalore",
  "area": "Central Bangalore",
  "avg_rating": "4.2",
  "total_ratings": "11114",
  "cuisine": [ "Desserts"],
  "tags": [],
  "recommended": 0,
  "costForTwo": null,
  "costForTwoString": "$$$",
  "deliveryCharge": 0,
  "minimumOrder": 0,
  "opened": 1,
  "deliveryTime": 35,
  "minDeliveryTime": 35,
  "maxDeliveryTime": 45,
  "slugs": {
    "restaurant": "corner-house-central-bangalore",
    "city": "bangalore"
  },
  "tmpClosed": false,
  "type": "D",
  "cityState": "Karnataka",
  "address": "45/3, Gopalkrishna Complex, Near Mayo Hall, Off Residency Road, Bangalore",
  "postalCode": 560001,
  "latLong": "12.973581,77.60931499999992",
  "cityDeliveryCharge": 30,
  "threshold": -1,
  "bannerMessage": "",
  "locality": "Residency Road",
  "parentId": 283,
  "nextCloseTime": [
    2016,
    12,
    21,
    23,
    0
  ],
  "delivery_fee_message": "Fixed Fee of ? 50.0 is applicable",
  "delivery_fee_type": 1,
  "unserviceable": false,
  "new": false,
  "veg": false,
  "select": false,
  "favorite": false,
  "imgUrl": "https://res.cloudinary.com/swiggy/image/upload/c_scale,f_auto,fl_lossy,h_134,q_80,w_269/r2akpwqkpsorqzr9x0eq",
  "active": true
},
{
  "id": 8147,
  "name": "Baba Da Dhaba",
  "uuid": "88794cab-e03d-4b3e-b588-c106815214a5",
  "city": "Bangalore",
  "area": "Central Bangalore",
  "avg_rating": "3.9",
  "total_ratings": "3698",
  "cloudinaryImageId": "sfwb13iyhvp1hf6kgnam",
  "cuisine": [
    "North Indian",
    "Biryani",
    "Desserts"
  ],
  "tags": [],
  "recommended": 0,
  "costForTwo": 36700,
  "costForTwoString": "$$$",
  "deliveryCharge": 0,
  "minimumOrder": 0,
  "opened": 1,
  "deliveryTime": 36,
  "minDeliveryTime": 36,
  "maxDeliveryTime": 46,
  "slugs": {
    "restaurant": "baba-da-dhaba-cbd-central-bangalore",
    "city": "bangalore"
  },
  "tmpClosed": false,
  "type": "F",
  "cityState": "Karnataka",
  "address": "135, 3rd Floor, Residency Road, Bengaluru, Karnataka 560025",
  "postalCode": 560001,
  "latLong": "12.96522,77.59916999999996",
  "cityDeliveryCharge": 30,
  "threshold": 250,
  "bannerMessage": "",
  "locality": "CBD",
  "parentId": 1299,
  "nextCloseTime": [
    2016,
    12,
    21,
    22,
    30
  ],
  "delivery_fee_type": 0,
  "unserviceable": false,
  "new": false,
  "veg": false,
  "select": false,
  "favorite": false,
  "imgUrl": "https://res.cloudinary.com/swiggy/image/upload/c_scale,f_auto,fl_lossy,h_134,q_80,w_269/sfwb13iyhvp1hf6kgnam",
  "active": true
}
]